setup.py
tencentyun_cos/__init__.py
tencentyun_cos/auth.py
tencentyun_cos/conf.py
tencentyun_cos/cos.py
tencentyun_cos.egg-info/PKG-INFO
tencentyun_cos.egg-info/SOURCES.txt
tencentyun_cos.egg-info/dependency_links.txt
tencentyun_cos.egg-info/requires.txt
tencentyun_cos.egg-info/top_level.txt