Metadata-Version: 1.0
Name: tencentyun-cos
Version: 1.0.2
Summary: python sdk for app.qcloud.com
Home-page: UNKNOWN
Author: jayli
Author-email: jayli@tencent.com
License: MIT License
Keywords: tencentyun,qcloud,cos
Platform: any
